{
  "advancement": "alchemancy:story/apply_property",
  "category": "alchemancy:properties",
  "icon": "minecraft:barrier",
  "priority": true,
  "name": "alchemancy.entry.missing_infusion_entries",
  "pages": [
    {
      "type": "patchouli:text",
      "text": "alchemancy.entry.missing_infusion_entries.page0"
    },
    {
      "type": "patchouli:link",
      "text": "alchemancy.entry.missing_infusion_entries.page1",
      "link_text": "alchemancy.entry.infusion_property.wiki_button",
      "url": "https://github.com/Cibernet83/Alchemancy/wiki/Infusion-Properties#absorbent"
    }
  ]
}