{
	"credit": "Made with Blockbench",
	"parent": "minecraft:block/block",
	"textures": {
		"0": "minecraft:block/sculk",
		"particle": "minecraft:block/sculk"
	},
	"elements": [
		{
			"from": [4, 0, 4],
			"to": [12, 10, 12],
			"faces": {
				"north": {"uv": [4, 6, 12, 16], "texture": "#0"},
				"east": {"uv": [4, 6, 12, 16], "texture": "#0"},
				"south": {"uv": [4, 6, 12, 16], "texture": "#0"},
				"west": {"uv": [4, 6, 12, 16], "texture": "#0"},
				"up": {"uv": [4, 4, 12, 12], "texture": "#0"},
				"down": {"uv": [4, 4, 12, 12], "texture": "#0"}
			}
		}
	]
}